secd/__init__.py
secd/secd.py
secd-0.0.11.dist-info/METADATA
secd-0.0.11.dist-info/WHEEL
secd-0.0.11.dist-info/licenses/LICENCE
secd-0.0.11.dist-info/RECORD
