Metadata-Version: 2.1
Name: secd
Version: 0.0.11
Summary: A package to work with kthcloud secd
Project-URL: Homepage, https://github.com/kthcloud/secd-pip
Project-URL: Bug Tracker, https://github.com/kthcloud/secd-pip/issues
Author-email: Emil Karlsson <emilk2@kth.se>, Pierre Le Fevre <pierrelf@kth.se>
License-File: LICENCE
Classifier: License :: OSI Approved :: MIT License
Classifier: Operating System :: OS Independent
Classifier: Programming Language :: Python :: 3
Requires-Python: >=3.7
Requires-Dist: python-dotenv
Requires-Dist: pyyaml
